SMSHubAPI/__init__.py
SMSHubAPI/api.py
SMSHubAPI/enums.py
SMSHubAPI/exceptions.py
simple_smshub_api-1.1.0.dist-info/licenses/LICENSE
simple_smshub_api-1.1.0.dist-info/METADATA
simple_smshub_api-1.1.0.dist-info/WHEEL
simple_smshub_api-1.1.0.dist-info/top_level.txt
simple_smshub_api-1.1.0.dist-info/RECORD
