Metadata-Version: 2.4
Name: Simple-SMSHub-API
Version: 1.1.0
Summary: Unofficial API for smshub.org
Home-page: https://github.com/dail45/SMSHub-API
Author: dail45
Keywords: requests threading
Classifier: Programming Language :: Python :: 3.11
Classifier: License :: OSI Approved :: MIT License
Classifier: Operating System :: OS Independent
Requires: mtrequests
Requires-Python: >=3.6
License-File: LICENSE
Requires-Dist: mtrequests
Dynamic: author
Dynamic: classifier
Dynamic: description
Dynamic: description-content-type
Dynamic: home-page
Dynamic: keywords
Dynamic: license-file
Dynamic: requires
Dynamic: requires-dist
Dynamic: requires-python
Dynamic: summary
